{
  "$comment": "generated by scripts/compile-schemas.py from assets/schemas.yaml; do not edit",
  "$defs": {
    "artifact": {
      "additionalProperties": true,
      "properties": {
        "artifactId": {
          "type": "string"
        },
        "description": {
          "type": "string"
        },
        "extensions": {
          "items": {
            "type": "string"
          },
          "type": "array"
        },
        "metadata": {
          "additionalProperties": true,
          "properties": {
            "a2a_context_id": {
              "type": "string"
            },
            "a2a_task_id": {
              "type": "string"
            },
            "agent": {
              "type": "string"
            },
            "entity_id": {
              "type": "string"
            },
            "run_id": {
              "type": "string"
            },
            "share_url": {
              "type": "string"
            },
            "type": {
              "type": "string"
            }
          },
          "required": [
            "type"
          ],
          "type": "object"
        },
        "name": {
          "type": "string"
        },
        "parts": {
          "items": {
            "$ref": "#/$defs/part"
          },
          "type": "array"
        }
      },
      "required": [
        "artifactId",
        "name",
        "description",
        "parts",
        "metadata"
      ],
      "type": "object"
    },
    "cohort": {
      "additionalProperties": true,
      "properties": {
        "discovery_subset": {
          "additionalProperties": true,
          "properties": {
            "definition": {
              "type": "string"
            },
            "n": {
              "type": "number"
            },
            "path": {
              "type": "string"
            }
          },
          "required": [
            "definition",
            "n",
            "path"
          ],
          "type": "object"
        },
        "exclusion_criteria": {
          "type": "string"
        },
        "holdout_subset": {
          "additionalProperties": true,
          "properties": {
            "definition": {
              "type": "string"
            },
            "n": {
              "type": "number"
            },
            "path": {
              "type": "string"
            }
          },
          "required": [
            "definition",
            "n",
            "path"
          ],
          "type": "object"
        },
        "id": {
          "type": "string"
        },
        "inclusion_criteria": {
          "type": "string"
        },
        "research_question": {
          "type": "string"
        },
        "run_id": {
          "type": "string"
        },
        "sampling": {
          "type": "string"
        },
        "source_data_sources": {
          "items": {
            "type": "string"
          },
          "type": "array"
        }
      },
      "required": [
        "id",
        "research_question",
        "inclusion_criteria",
        "exclusion_criteria",
        "sampling",
        "source_data_sources",
        "discovery_subset",
        "holdout_subset",
        "run_id"
      ],
      "type": "object"
    },
    "dataset": {
      "additionalProperties": true,
      "properties": {
        "covers_laws": {
          "items": {
            "type": "string"
          },
          "type": "array"
        },
        "definition": {
          "type": "string"
        },
        "id": {
          "type": "string"
        },
        "n": {
          "type": "number"
        },
        "sampling": {
          "type": "string"
        },
        "source": {
          "type": "string"
        },
        "variables": {
          "items": {
            "type": "string"
          },
          "type": "array"
        }
      },
      "required": [
        "id",
        "definition",
        "source",
        "n",
        "sampling",
        "variables",
        "covers_laws"
      ],
      "type": "object"
    },
    "part": {
      "additionalProperties": true,
      "properties": {
        "kind": {
          "type": "string"
        },
        "metadata": {
          "type": "object"
        }
      },
      "required": [
        "kind"
      ],
      "type": "object"
    }
  },
  "$id": "asta-research-step/cohort_assembly.schema.json",
  "$schema": "https://json-schema.org/draft/2020-12/schema",
  "additionalProperties": false,
  "properties": {
    "artifacts": {
      "items": {
        "$ref": "#/$defs/artifact"
      },
      "type": "array"
    },
    "cohort": {
      "$ref": "#/$defs/cohort"
    },
    "datasets": {
      "items": {
        "$ref": "#/$defs/dataset"
      },
      "type": "array"
    }
  },
  "required": [
    "cohort",
    "datasets",
    "artifacts"
  ],
  "title": "cohort_assembly",
  "type": "object"
}
